{
  "$type": "Murder.Assets.PrefabAsset",
  "ShowOnPrefabSelector": true,
  "Dimensions": {
    "Origin": {
      "X": 0,
      "Y": 0
    },
    "Size": {
      "X": 1,
      "Y": 1
    }
  },
  "Name": "Camera man",
  "Guid": "fce7634c-9ba9-4279-9fa0-129fc9816287",
  "entity": {
    "IsDeactivated": false,
    "ActivateWithParent": false,
    "guid": "468bd21e-2bed-404f-bb75-8d995436e35d",
    "name": "",
    "components": {
      "Murder.Components.CameraFollowComponent, Murder, Version=1.0.0.0, Culture=neutral, PublicKeyToken=null": {
        "$type": "Murder.Components.CameraFollowComponent",
        "Enabled": true,
        "Style": 0
      },
      "Murder.Components.PositionComponent, Murder, Version=1.0.0.0, Culture=neutral, PublicKeyToken=null": {
        "$type": "Murder.Components.PositionComponent",
        "x": 0,
        "y": 0
      }
    }
  }
}