{
  "$type": "Murder.Assets.CharacterAsset",
  "Owner": "00000000-0000-0000-0000-000000000000",
  "Name": "Hello",
  "Guid": "a76c51b9-e048-46d3-a66f-616e636336ee",
  "situations": {
    "0": {
      "Id": 0,
      "Name": "Hello",
      "Dialogs": [
        {
          "PlayUntil": -1,
          "Id": 0,
          "Requirements": [],
          "Lines": [],
          "IsChoice": false
        },
        {
          "PlayUntil": 1,
          "Id": 1,
          "Requirements": [],
          "Lines": [
            {
              "Text": {
                "Id": "40f7d8c1-b986-4d47-9469-3a67e511c854"
              }
            }
          ],
          "GoTo": -1,
          "IsChoice": false
        },
        {
          "PlayUntil": -1,
          "Id": 2,
          "Requirements": [],
          "Lines": [
            {
              "Text": {
                "Id": "a0177851-ca14-4e22-85f4-2078c4ae8bf7"
              }
            },
            {
              "Text": {
                "Id": "8ccc2c6d-ca2f-4a86-a40f-7e3e1bd7e8ed"
              }
            },
            {
              "Text": {
                "Id": "456d30c3-11b3-4e2c-ba3e-005a4f950d79"
              }
            }
          ],
          "IsChoice": false
        }
      ],
      "Edges": {
        "0": {
          "Kind": 1,
          "Dialogs": [
            1,
            2
          ]
        }
      }
    }
  },
  "components": {},
  "portraits": {}
}